{
	"Resource Groups": {
		"description": "",
		"name": "Metrics",
		"order": 100,
		"templates": [
			{
				"id": "Workbooks/Resource Groups/Virtual Machines",
				"fileName": "Resource Groups-Virtual Machines.json",
				"author": "Microsoft",
				"name": "Virtual machines"
			},
			{
				"id": "Workbooks/Resource Groups/Storage Accounts",
				"fileName": "Resource Groups-Storage Accounts.json",
				"author": "Microsoft",
				"name": "Storage accounts"
			},
			{
				"id": "Workbooks/Resource Groups/Sql databases",
				"fileName": "Resource Groups-Sql databases.json",
				"author": "Microsoft",
				"name": "Sql databases"
			}
		]
	}
}